Metadata-Version: 2.1
Name: odoo13-addon-shopinvader-payment-sips
Version: 13.0.1.0.1
Summary: Shopinvader REST Services for Worldline SIPS Payments
Home-page: https://github.com/shopinvader/odoo-shopinvader-payment
Author: ACSONE SA/NV
License: AGPL-3
Platform: UNKNOWN
Classifier: Programming Language :: Python
Classifier: Framework :: Odoo
Classifier: License :: OSI Approved :: GNU Affero General Public License v3
Requires-Python: >=3.5
Requires-Dist: odoo13-addon-invader-payment-sips
Requires-Dist: odoo13-addon-shopinvader-payment
Requires-Dist: odoo (<13.1dev,>=13.0a)
